MANIFEST.in
account_invoice_view.xml
res_partner_view.xml
setup.py
./__init__.py
./__openerp__.py
./account_report_company.py
./report/__init__.py
./report/account_invoice_report.py
i18n/account_report_company.pot
i18n/bs.po
i18n/cs.po
i18n/da.po
i18n/de.po
i18n/en_GB.po
i18n/es.po
i18n/fr.po
i18n/hr.po
i18n/hu.po
i18n/it.po
i18n/mn.po
i18n/nl.po
i18n/pl.po
i18n/pt.po
i18n/pt_BR.po
i18n/ro.po
i18n/ru.po
i18n/sl.po
i18n/tr.po
i18n/vi.po
i18n/zh_CN.po
i18n/zh_TW.po
openerp_account_report_company.egg-info/PKG-INFO
openerp_account_report_company.egg-info/SOURCES.txt
openerp_account_report_company.egg-info/dependency_links.txt
openerp_account_report_company.egg-info/requires.txt
openerp_account_report_company.egg-info/top_level.txt
report/account_invoice_report_view.xml